README.md
setup.py
DBZ.egg-info/PKG-INFO
DBZ.egg-info/SOURCES.txt
DBZ.egg-info/dependency_links.txt
DBZ.egg-info/requires.txt
DBZ.egg-info/top_level.txt
MLB/MLB.py
MLB/__init__.py