Metadata-Version: 1.1
Name: DBZ
Version: 0.0.1
Summary: hogehoge
Home-page: https://github.com/micin-jp/DBZ
Author: mucunwuxian
Author-email: taketo_kimura@micin.jp
License: UNKNOWN
Keywords: hogehoge
Platform: UNKNOWN
Classifier: Development Status :: 3 - Alpha
